okdata_aws-5.0.0-py3.13-nspkg.pth
okdata/aws/__init__.py
okdata/aws/logging.py
okdata/aws/ssm.py
okdata/aws/status/__init__.py
okdata/aws/status/model.py
okdata/aws/status/sdk.py
okdata/aws/status/wrapper.py
okdata_aws-5.0.0.dist-info/METADATA
okdata_aws-5.0.0.dist-info/WHEEL
okdata_aws-5.0.0.dist-info/namespace_packages.txt
okdata_aws-5.0.0.dist-info/top_level.txt
okdata_aws-5.0.0.dist-info/RECORD
