Metadata-Version: 2.4
Name: okdata-aws
Version: 5.0.0
Summary: Collection of helpers for working with AWS
Home-page: https://github.com/oslokommune/okdata-aws
Author: Oslo Origo
Author-email: dataplattform@oslo.kommune.no
Classifier: Development Status :: 5 - Production/Stable
Classifier: License :: OSI Approved :: MIT License
Classifier: Operating System :: OS Independent
Classifier: Programming Language :: Python :: 3
Classifier: Programming Language :: Python :: 3.10
Classifier: Programming Language :: Python :: 3.11
Classifier: Programming Language :: Python :: 3.12
Classifier: Programming Language :: Python :: 3.13
Requires-Dist: boto3
Requires-Dist: okdata-sdk<4,>=3.3
Requires-Dist: requests
Requires-Dist: starlette<1.0.0,>=0.36.3
Requires-Dist: structlog
Dynamic: author
Dynamic: author-email
Dynamic: classifier
Dynamic: description
Dynamic: description-content-type
Dynamic: home-page
Dynamic: requires-dist
Dynamic: summary
